README.md
setup.py
mendel_opt.egg-info/PKG-INFO
mendel_opt.egg-info/SOURCES.txt
mendel_opt.egg-info/dependency_links.txt
mendel_opt.egg-info/requires.txt
mendel_opt.egg-info/top_level.txt
mendelopt/__init__.py
mendelopt/generation.py
mendelopt/mutation.py
mendelopt/optimizer.py
mendelopt/reproduction.py